paypalrestsdk/__init__.py
paypalrestsdk/api.py
paypalrestsdk/config.py
paypalrestsdk/exceptions.py
paypalrestsdk/invoice_templates.py
paypalrestsdk/invoices.py
paypalrestsdk/notifications.py
paypalrestsdk/openid_connect.py
paypalrestsdk/payment_experience.py
paypalrestsdk/payments.py
paypalrestsdk/resource.py
paypalrestsdk/util.py
paypalrestsdk/vault.py
paypalrestsdk/data/DigiCertHighAssuranceEVRootCA.crt.pem
paypalrestsdk/data/DigiCertSHA2ExtendedValidationServerCA.crt.pem
paypalrestsdk-1.13.2.dist-info/LICENSE.txt
paypalrestsdk-1.13.2.dist-info/METADATA
paypalrestsdk-1.13.2.dist-info/WHEEL
paypalrestsdk-1.13.2.dist-info/top_level.txt
paypalrestsdk-1.13.2.dist-info/RECORD
